km2pg
