Metadata-Version: 1.0
Name: km2pg
Version: 0.2.0.1
Summary: Load kissmetrics website analytics data from an s3 bucket into a postgres database
Home-page: http://github.com/shashank025/km2pg
Author: Shashank Ramaprasad
Author-email: shashank.ramaprasad+km2pg@gmail.com
License: MIT
Platform: UNKNOWN
